chainlit/__init__.py
chainlit/__main__.py
chainlit/_utils.py
chainlit/action.py
chainlit/auth/__init__.py
chainlit/auth/cookie.py
chainlit/auth/jwt.py
chainlit/cache.py
chainlit/callbacks.py
chainlit/chat_context.py
chainlit/chat_settings.py
chainlit/cli/__init__.py
chainlit/config.py
chainlit/context.py
chainlit/copilot/dist/index.js
chainlit/data/__init__.py
chainlit/data/acl.py
chainlit/data/base.py
chainlit/data/chainlit_data_layer.py
chainlit/data/dynamodb.py
chainlit/data/literalai.py
chainlit/data/sql_alchemy.py
chainlit/data/storage_clients/__init__.py
chainlit/data/storage_clients/azure.py
chainlit/data/storage_clients/azure_blob.py
chainlit/data/storage_clients/base.py
chainlit/data/storage_clients/gcs.py
chainlit/data/storage_clients/s3.py
chainlit/data/utils.py
chainlit/discord/__init__.py
chainlit/discord/app.py
chainlit/element.py
chainlit/emitter.py
chainlit/frontend/dist/assets/DailyMotion-CfCWbJWf.js
chainlit/frontend/dist/assets/DailyMotion-CfCWbJWf.js.map
chainlit/frontend/dist/assets/Dataframe-ChQ5yOX1.js
chainlit/frontend/dist/assets/Dataframe-ChQ5yOX1.js.map
chainlit/frontend/dist/assets/Facebook-e__wOnsU.js
chainlit/frontend/dist/assets/Facebook-e__wOnsU.js.map
chainlit/frontend/dist/assets/FilePlayer-D-jOqljd.js
chainlit/frontend/dist/assets/FilePlayer-D-jOqljd.js.map
chainlit/frontend/dist/assets/Kaltura-ikHUa8vL.js
chainlit/frontend/dist/assets/Kaltura-ikHUa8vL.js.map
chainlit/frontend/dist/assets/Mixcloud-r8VVKVDq.js
chainlit/frontend/dist/assets/Mixcloud-r8VVKVDq.js.map
chainlit/frontend/dist/assets/Mux-SYt4v-u7.js
chainlit/frontend/dist/assets/Mux-SYt4v-u7.js.map
chainlit/frontend/dist/assets/Preview-C7SI8k5I.js
chainlit/frontend/dist/assets/Preview-C7SI8k5I.js.map
chainlit/frontend/dist/assets/SoundCloud-CL5VEDAg.js
chainlit/frontend/dist/assets/SoundCloud-CL5VEDAg.js.map
chainlit/frontend/dist/assets/Streamable-CPaWmpz8.js
chainlit/frontend/dist/assets/Streamable-CPaWmpz8.js.map
chainlit/frontend/dist/assets/Twitch-BYdj7q4k.js
chainlit_jlfel-2.6.9.dist-info/METADATA
chainlit_jlfel-2.6.9.dist-info/WHEEL
chainlit_jlfel-2.6.9.dist-info/entry_points.txt
chainlit_jlfel-2.6.9.dist-info/RECORD
